pylogctx/__init__.py
pylogctx/celery.py
pylogctx/compat.py
pylogctx/core.py
pylogctx/django.py
pylogctx/helpers.py
pylogctx-1.12.dist-info/DESCRIPTION.rst
pylogctx-1.12.dist-info/METADATA
pylogctx-1.12.dist-info/RECORD
pylogctx-1.12.dist-info/WHEEL
pylogctx-1.12.dist-info/metadata.json
pylogctx-1.12.dist-info/top_level.txt
