Metadata-Version: 2.0
Name: pylogctx
Version: 1.12
Summary: Adding context to log records
Home-page: https://github.com/novafloss/pylogctx
Author: Lev Orekhov
Author-email: lev.orekhov@gmail.com
License: BSD
Keywords: logging context logging django
Platform: UNKNOWN
Classifier: Intended Audience :: Developers
Classifier: Programming Language :: Python
Classifier: Programming Language :: Python :: 2
Classifier: Programming Language :: Python :: 3
Classifier: Programming Language :: Python :: 3.5
Classifier: Programming Language :: Python :: 3.6
Classifier: Operating System :: OS Independent
Classifier: Topic :: Software Development :: Libraries
Classifier: Topic :: Software Development :: Libraries :: Python Modules
